{"trial_id": "0054", "hyperparameters": {"space": [{"class_name": "Choice", "config": {"name": "activation", "default": "relu", "conditions": [], "values": ["relu", "tanh"], "ordered": false}}, {"class_name": "Int", "config": {"name": "units_1", "default": null, "conditions": [], "min_value": 16, "max_value": 128, "step": 16, "sampling": "linear"}}, {"class_name": "Int", "config": {"name": "units_2", "default": null, "conditions": [], "min_value": 8, "max_value": 64, "step": 8, "sampling": "linear"}}, {"class_name": "Float", "config": {"name": "reg_value", "default": 1e-05, "conditions": [], "min_value": 1e-05, "max_value": 0.01, "step": null, "sampling": "log"}}, {"class_name": "Choice", "config": {"name": "regularizer", "default": "l1", "conditions": [], "values": ["l1", "l2"], "ordered": false}}, {"class_name": "Float", "config": {"name": "learning_rate", "default": 1e-05, "conditions": [], "min_value": 1e-05, "max_value": 0.01, "step": null, "sampling": "log"}}], "values": {"activation": "relu", "units_1": 128, "units_2": 16, "reg_value": 0.004114565089723973, "regularizer": "l2", "learning_rate": 1.2365031171989392e-05, "tuner/epochs": 4, "tuner/initial_epoch": 0, "tuner/bracket": 2, "tuner/round": 0}}, "metrics": {"metrics": {"accuracy": {"direction": "max", "observations": [{"value": [0.7671286463737488], "step": 3}]}, "loss": {"direction": "min", "observations": [{"value": [0.7954005599021912], "step": 3}]}, "val_accuracy": {"direction": "max", "observations": [{"value": [0.7808279395103455], "step": 3}]}, "val_loss": {"direction": "min", "observations": [{"value": [0.7702828049659729], "step": 3}]}}}, "score": 0.7808279395103455, "best_step": 3, "status": "COMPLETED", "message": null}